peasyTracker.py
peasyTracker-0.0.1.dist-info/LICENSE
peasyTracker-0.0.1.dist-info/METADATA
peasyTracker-0.0.1.dist-info/WHEEL
peasyTracker-0.0.1.dist-info/top_level.txt
peasyTracker-0.0.1.dist-info/RECORD
