Metadata-Version: 2.1
Name: peasyTracker
Version: 0.0.1
Summary: Adaptation of Jean-Yves Tinevez's Simple Tracker in Python
Author-email: Jacques Battaglia <jacques.battaglia@cnrs.fr>, Jean-Baptiste Deloges <jean-baptiste.deloges@sorbonne-universite.fr>, Olivier Couture <olivier.couture@cnrs.fr>
Project-URL: Homepage, https://github.com/Lab-Imag-Bio/PeasyTracker
Project-URL: Issues, https://github.com/Lab-Imag-Bio/PeasyTracker/issues
Classifier: Programming Language :: Python :: 3.10
Classifier: Programming Language :: Python :: 3.11
Classifier: Programming Language :: Python :: 3.12
Classifier: License :: OSI Approved :: MIT License
Classifier: Operating System :: OS Independent
Requires-Python: >=3.10
License-File: LICENSE
Requires-Dist: numpy
Requires-Dist: scipy
